pgskewer/__about__.py
pgskewer/__init__.py
pgskewer/cli.py
pgskewer/helpers.py
pgskewer/migrations.py
pgskewer-0.1.0.dist-info/METADATA
pgskewer-0.1.0.dist-info/WHEEL
pgskewer-0.1.0.dist-info/entry_points.txt
pgskewer-0.1.0.dist-info/RECORD
