Metadata-Version: 2.4
Name: pgskewer
Version: 0.1.0
Summary: EDWH pgqueuer pipeline (pg-skEWer)
Author-email: Robin van der Noord <robin.vdn@educationwarehouse.nl>
Requires-Python: >=3.12
Requires-Dist: anyio
Requires-Dist: asyncpg
Requires-Dist: edwh-uuid7
Requires-Dist: pgqueuer<0.25
Requires-Dist: python-dotenv
Requires-Dist: uvloop
Provides-Extra: dev
Requires-Dist: edwh; extra == 'dev'
Requires-Dist: edwh-migrate; extra == 'dev'
Requires-Dist: hatch; extra == 'dev'
Requires-Dist: psycopg2-binary; extra == 'dev'
Requires-Dist: pydal; extra == 'dev'
Requires-Dist: pytest; extra == 'dev'
Requires-Dist: pytest-cov; extra == 'dev'
Requires-Dist: python-semantic-release<8; extra == 'dev'
Provides-Extra: migrate
Requires-Dist: edwh-migrate; extra == 'migrate'
Requires-Dist: psycopg2-binary; extra == 'migrate'
Requires-Dist: pydal; extra == 'migrate'
